{"run_number": "1717237662406149", "step_name": "elasticnet_param", "task_id": "6", "attempt_id": 0, "name": "df_visits", "content_type": "gzip+pickle-v2", "type": "metaflow.artifact", "sha": "db5ea20df1e3987c2a88b2bc7fa91760e75c2951", "ds_type": "local", "location": ":root:/home/sakthi/healthcaremlops/.metaflow", "flow_id": "RegressionFlow", "user_name": "sakthi", "tags": [], "system_tags": ["python_version:3.11.0", "user:sakthi", "runtime:dev", "metaflow_version:2.12.0"], "ts_epoch": 1717237682190}